{
  "texts": {
    "en_US": {
      "title": "WarfPlanner",
      "open_sidebar": "Open sidebar",
      "link": "Link",
      "menu": {
        "upgrades": "Upgrades",
        "materials": "Materials",
        "import_export": "Import/Export",
        "settings": "Settings",
        "about": "About"
      },
      "button": {
        "reload_app": "Reload app",
        "download_arknights_data": "Download arknights data",
        "load_materials": "Load materials",
        "edit_materials": "Edit materials",
        "load_characters": "Load characters",
        "add_character": "Add character",
        "show_cn_only_characters": "Show CN only characters",
        "load_settings": "Load settings",
        "load_import_export": "Load import/export",
        "load_about": "Load about"
      },
      "placeholder": {
        "search_character": "Search character..."
      },
      "label": {
        "main": "Main",
        "elite": "Elite",
        "level": "Level",
        "all_skills": "All skills",
        "skills": "Skills",
        "modules": "Modules",
        "elite_from": "Elite from",
        "elite_to": "Elite to",
        "level_from": "Level from",
        "level_to": "Level to",
        "skill_from": "Skill from",
        "skill_to": "Skill to",
        "module_from": "Module from",
        "module_to": "Module to",
        "from": "From",
        "to": "To"
      },
      "materials": {
        "main": "Main",
        "module": "Module",
        "exp": "Exp cards",
        "skill": "Skill books",
        "orirock": "Orirock",
        "sugar": "Sugar",
        "polyester": "Polyester",
        "oriron": "Oriron",
        "keton": "Keton",
        "device": "Device",
        "grindstone": "Grindstone",
        "kohl": "Kohl",
        "solvent": "Solvent",
        "gel": "Gel",
        "crystalline": "Crystalline",
        "manganese": "Manganese",
        "alloy": "Alloy",
        "cutting_fluid": "Cutting fluid",
        "salt": "Salt",
        "rma70": "RMA70",
        "???_1": "??? 2",
        "???_2": "??? 2",
        "t5_1": "Craftable T5 (old)",
        "t5_2": "Craftable T5 (new)",
        "vanguard_chips": "Vanguard chips",
        "guard_chips": "Guard chips",
        "defender_chips": "Defender chips",
        "sniper_chips": "Sniper chips",
        "caster_chips": "Caster chips",
        "medic_chips": "Medic chips",
        "supporter_chips": "Supporter chips",
        "specialist_chips": "Specialist chips"
      },
      "are_you_sure": "Are you sure?",
      "settings": {
        "title": "Settings",
        "settings": {
          "title": "Settings",
          "scale": "Scale",
          "scale-tooltip": "Scale of UI elements [50 - 1000] (100 = 100%)",
          "theme": "Theme",
          "theme-tooltip": "Color theme",
          "theme-light": "Light",
          "theme-dark": "Dark",
          "language": "Language",
          "language-tooltip": "Language",
          "language-en_us": "English (US)"
        },
        "app": {
          "title": "Application",
          "port": "Port",
          "port-tooltip": "Port on witch application wil start [0-65535] (0 = random)",
          "environment": "Environment",
          "environment-tooltip": "In development will show more options",
          "environment-development": "Development",
          "environment-production": "Production",
          "server": "Server",
          "server-tooltip": "Changes how application will start",
          "server-flask": "Flask (single thread development server)",
          "server-waitress": "Waitress (multi threaded production server)",
          "mode": "Mode",
          "mode-tooltip": "Changes how application will be accessed",
          "mode-browser": "Browser (access only via browser)",
          "mode-window": "Window (access only via separate application window)"
        },
        "arknights": {
          "title": "Arknights",
          "force_download_data": "Force download data",
          "force_download_data-tooltip": "Force download arknights data files if they already exist [true / false]",
          "force_download_images": "Force download images",
          "force_download_images-tooltip": "Force download arknights images if they already exist [true / false]"
        }
      },
      "import_export": {
        "title": "Import/Export",
        "import": "Import",
        "export": "Export",
        "import_data": "Import data...",
        "copy_export_data": "Copy export data",
        "penguin-statistics": "Penguin Statistics",
        "penguin-statistics-url": "https://penguin-stats.io/planner",
        "gamepress": "Game Press",
        "gamepress-url": "https://gamepress.gg/arknights/tools/arknights-operator-planner"
      },
      "about": {
        "title": "About",
        "description_1": "WarfPlanner is a tool for Arknights mobile game. It allows you to plan your characters upgrades, and see how much resources you have and need.",
        "description_2": "It uses AI to recognize materials from screenshots or open client of depot screen, and OCR to recognize amounts and type of materials."

      }
    }
  }
}